{"original_content": "# CloudFlow User Guide Welcome to CloudFlow, the modern workflow automation platform that helps you connect your apps, automate repetitive tasks, and build powerful integrations without writing code. ## Table of Contents 1. [Getting Started](#getting-started) 2. [Workflow Creation](#workflow-creation) 3. [Available Actions](#available-actions) 4. [Variables and Expressions](#variables-and-expressions) 5. [Scheduling](#scheduling) 6. [Error Handling](#error-handling) 7. [Workflow Limits](#workflow-limits) 8. [Best Practices](#best-practices) 9. [Common Workflow Patterns](#common-workflow-patterns) ## Getting Started ### Account Setup Creating your CloudFlow account takes just a few minutes: 1. Navigate to https://app.cloudflow.io/signup 2. Enter your email address and create a strong password 3. Verify your email address by clicking the link sent to your inbox 4. Complete your profile by providing your organization name and use case 5. Choose your plan (Free, Professional, or Enterprise) Once your account is created, you'll be redirected to your CloudFlow dashboard where you can start building workflows immediately. ### Your First Workflow Let's create a simple workflow that sends you a Slack notification when a new file is uploaded to your Google Drive: 1. Click the **\"Create Workflow\"** button in the top-right corner 2. Give your workflow a name: \"Google Drive to Slack Notifier\" 3. Select **\"Google Drive - New File\"** as your trigger 4. Authenticate your Google Drive account when prompted 5. Choose the folder you want to monitor 6. Click **\"Add Action\"** and select **\"Slack - Send Message\"** 7. Authenticate your Slack account 8. Select the channel where you want to receive notifications 9. Customize your message using variables: `New file uploaded: {{trigger.file.name}}` 10. Click **\"Save & Activate\"** to enable your workflow Congratulations! Your first workflow is now live. Every time a file is added to the specified Google Drive folder, you'll receive a Slack notification. ## Workflow Creation CloudFlow offers multiple ways to create and manage workflows, giving you the flexibility to work in the way that suits you best. ### Visual Editor The Visual Editor is CloudFlow's drag-and-drop interface for building workflows without code. It's perfect for users who prefer a graphical approach: **Key Features:** - Drag-and-drop action blocks from the sidebar - Visual connections between steps show your workflow logic - Inline configuration for each action - Real-time validation and error checking - Test mode to run your workflow with sample data **Using the Visual Editor:** 1.", "enhanced_content": "Google Drive, workflow, User Guide, Visual Editor, Google, automate repetitive, repetitive tasks | CloudFlow, Slack, Contents 1, Workflow Creation](#workflow-creation, Common Workflow Patterns](#common-workflow\n\n# CloudFlow User Guide Welcome to CloudFlow, the modern workflow automation platform that helps you connect your apps, automate repetitive tasks, and build powerful integrations without writing code. ## Table of Contents 1. [Getting Started](#getting-started) 2. [Workflow Creation](#workflow-creation) 3. [Available Actions](#available-actions) 4. [Variables and Expressions](#variables-and-expressions) 5. [Scheduling](#scheduling) 6. [Error Handling](#error-handling) 7. [Workflow Limits](#workflow-limits) 8. [Best Practices](#best-practices) 9. [Common Workflow Patterns](#common-workflow-patterns) ## Getting Started ### Account Setup Creating your CloudFlow account takes just a few minutes: 1. Navigate to https://app.cloudflow.io/signup 2. Enter your email address and create a strong password 3. Verify your email address by clicking the link sent to your inbox 4. Complete your profile by providing your organization name and use case 5. Choose your plan (Free, Professional, or Enterprise) Once your account is created, you'll be redirected to your CloudFlow dashboard where you can start building workflows immediately. ### Your First Workflow Let's create a simple workflow that sends you a Slack notification when a new file is uploaded to your Google Drive: 1. Click the **\"Create Workflow\"** button in the top-right corner 2. Give your workflow a name: \"Google Drive to Slack Notifier\" 3. Select **\"Google Drive - New File\"** as your trigger 4. Authenticate your Google Drive account when prompted 5. Choose the folder you want to monitor 6. Click **\"Add Action\"** and select **\"Slack - Send Message\"** 7. Authenticate your Slack account 8. Select the channel where you want to receive notifications 9. Customize your message using variables: `New file uploaded: {{trigger.file.name}}` 10. Click **\"Save & Activate\"** to enable your workflow Congratulations! Your first workflow is now live. Every time a file is added to the specified Google Drive folder, you'll receive a Slack notification. ## Workflow Creation CloudFlow offers multiple ways to create and manage workflows, giving you the flexibility to work in the way that suits you best. ### Visual Editor The Visual Editor is CloudFlow's drag-and-drop interface for building workflows without code. It's perfect for users who prefer a graphical approach: **Key Features:** - Drag-and-drop action blocks from the sidebar - Visual connections between steps show your workflow logic - Inline configuration for each action - Real-time validation and error checking - Test mode to run your workflow with sample data **Using the Visual Editor:** 1.", "enrichment_type": "fast", "metadata": {"code_ratio": 0.02, "processing_time_ms": 79.84, "keyword_count": 10, "entity_count": 10}, "keywords": ["Google Drive", "workflow", "User Guide", "Visual Editor", "Google", "automate repetitive", "repetitive tasks", "Drive", "automation platform", "build powerful"], "questions": [], "summary": "", "entities": {"ORG": ["CloudFlow", "Slack"], "LAW": ["Contents 1"], "PERSON": ["Workflow Creation](#workflow-creation", "Common Workflow Patterns](#common-workflow"], "FAC": ["Google Drive", "Google Drive - New File"], "WORK_OF_ART": ["Google Drive to", "Slack - Send Message"], "PRODUCT": ["Google Drive"]}, "contextual_prefix": ""}