{"original_content": "**Technology**: Node.js with Express.js framework **Replicas**: 12 pods (production), auto-scaling 8-20 based on CPU **Resource Allocation**: 2 vCPU, 4GB RAM per pod **Key Responsibilities**: - JWT token validation (delegated to Auth Service for initial validation) - Rate limiting: 1000 requests per minute per API key (sliding window) - Request/response transformation and validation using JSON Schema - Routing to downstream services based on URL path patterns - CORS handling for web clients - Request/response logging and correlation ID injection **Critical Endpoints**: - `POST /api/v1/workflows` - Create new workflow - `GET /api/v1/workflows/:id` - Retrieve workflow status - `POST /api/v1/workflows/:id/execute` - Trigger workflow execution - `GET /api/v1/workflows/:id/history` - Get execution history **Dependencies**: - Auth Service (for token validation) - Redis (for rate limiting counters) - All downstream microservices **Performance Targets**: - P50 latency: < 50ms - P99 latency: < 200ms - Throughput: 10,000 RPS sustained --- ### Auth Service **Purpose**: Centralized authentication and authorization service handling user identity, token generation, and permission validation. **Technology**: Go with gRPC for internal communication, REST for external **Replicas**: 8 pods (production), auto-scaling 6-12 **Resource Allocation**: 1 vCPU, 2GB RAM per pod **Key Responsibilities**: - User authentication via multiple providers (OAuth2, SAML, local credentials) - JWT token generation and validation (RS256 algorithm) - Role-based access control (RBAC) with fine-grained permissions - Session management with Redis-backed storage - API key generation and validation for service accounts - MFA enforcement for administrative operations **Authentication Flow**: ``` Client Request \u2192 API Gateway \u2192 Auth Service \u2502 \u251c\u2500 Validate credentials \u251c\u2500 Check MFA if required \u251c\u2500 Generate JWT (15min expiry) \u251c\u2500 Generate refresh token (7 days) \u2514\u2500 Store session in Redis ``` **Token Structure**: - Access Token: JWT with 15-minute expiry - Refresh Token: Opaque token with 7-day expiry, stored in PostgreSQL - Claims: user_id, email, roles[], permissions[], tenant_id **Security Features**: - Password hashing: Argon2id with 64MB memory, 4 iterations - Token rotation on refresh to prevent replay attacks - Brute force protection: 5 failed attempts \u2192 15-minute lockout - Secrets stored in HashiCorp Vault, rotated every 90 days **Performance Targets**: - Token validation: < 10ms (P99) - Token generation: < 50ms (P99) - Throughput: 5,000 RPS for validation operations --- ### Workflow Engine **Purpose**: Core orchestration service that executes workflow definitions, manages state transitions, and coordinates task execution across distributed systems.", "enhanced_content": "Critical Endpoints, Auth Service, JSON Schema, Resource Allocation, Performance Targets, Rate limiting, Key Responsibilities | Express.js, CPU, JSON Schema - Routing, Generate, RS256\n\n**Technology**: Node.js with Express.js framework **Replicas**: 12 pods (production), auto-scaling 8-20 based on CPU **Resource Allocation**: 2 vCPU, 4GB RAM per pod **Key Responsibilities**: - JWT token validation (delegated to Auth Service for initial validation) - Rate limiting: 1000 requests per minute per API key (sliding window) - Request/response transformation and validation using JSON Schema - Routing to downstream services based on URL path patterns - CORS handling for web clients - Request/response logging and correlation ID injection **Critical Endpoints**: - `POST /api/v1/workflows` - Create new workflow - `GET /api/v1/workflows/:id` - Retrieve workflow status - `POST /api/v1/workflows/:id/execute` - Trigger workflow execution - `GET /api/v1/workflows/:id/history` - Get execution history **Dependencies**: - Auth Service (for token validation) - Redis (for rate limiting counters) - All downstream microservices **Performance Targets**: - P50 latency: < 50ms - P99 latency: < 200ms - Throughput: 10,000 RPS sustained --- ### Auth Service **Purpose**: Centralized authentication and authorization service handling user identity, token generation, and permission validation. **Technology**: Go with gRPC for internal communication, REST for external **Replicas**: 8 pods (production), auto-scaling 6-12 **Resource Allocation**: 1 vCPU, 2GB RAM per pod **Key Responsibilities**: - User authentication via multiple providers (OAuth2, SAML, local credentials) - JWT token generation and validation (RS256 algorithm) - Role-based access control (RBAC) with fine-grained permissions - Session management with Redis-backed storage - API key generation and validation for service accounts - MFA enforcement for administrative operations **Authentication Flow**: ``` Client Request \u2192 API Gateway \u2192 Auth Service \u2502 \u251c\u2500 Validate credentials \u251c\u2500 Check MFA if required \u251c\u2500 Generate JWT (15min expiry) \u251c\u2500 Generate refresh token (7 days) \u2514\u2500 Store session in Redis ``` **Token Structure**: - Access Token: JWT with 15-minute expiry - Refresh Token: Opaque token with 7-day expiry, stored in PostgreSQL - Claims: user_id, email, roles[], permissions[], tenant_id **Security Features**: - Password hashing: Argon2id with 64MB memory, 4 iterations - Token rotation on refresh to prevent replay attacks - Brute force protection: 5 failed attempts \u2192 15-minute lockout - Secrets stored in HashiCorp Vault, rotated every 90 days **Performance Targets**: - Token validation: < 10ms (P99) - Token generation: < 50ms (P99) - Throughput: 5,000 RPS for validation operations --- ### Workflow Engine **Purpose**: Core orchestration service that executes workflow definitions, manages state transitions, and coordinates task execution across distributed systems.", "enrichment_type": "fast", "metadata": {"code_ratio": 0.11, "processing_time_ms": 88.83, "keyword_count": 10, "entity_count": 10}, "keywords": ["Critical Endpoints", "Auth Service", "JSON Schema", "Resource Allocation", "Performance Targets", "Rate limiting", "Key Responsibilities", "JWT token", "token generation", "CORS handling"], "questions": [], "summary": "", "entities": {"ORG": ["Express.js", "CPU", "Auth Service", "API", "POST"], "PERSON": ["JSON Schema - Routing", "Generate"], "PRODUCT": ["RS256"], "GPE": ["Redis", "PostgreSQL"]}, "contextual_prefix": ""}