{"original_content": "# CloudFlow Platform - System Architecture Overview **Document Version:** 2.3.1 **Last Updated:** January 15, 2026 **Owner:** Platform Architecture Team **Status:** Production ## Executive Summary CloudFlow is a distributed, cloud-native workflow automation platform designed to orchestrate complex business processes at scale. The platform processes over 2.5 million workflow executions daily with an average P99 latency of 180ms for API operations and 4.2 seconds for workflow execution. This document provides a comprehensive overview of the system architecture, including microservices design, data flow patterns, infrastructure decisions, and operational considerations. ## Table of Contents 1. [High-Level Architecture](#high-level-architecture) 2. [Microservices Breakdown](#microservices-breakdown) 3. [Data Flow Architecture](#data-flow-architecture) 4. [Database Architecture](#database-architecture) 5. [Message Queue Patterns](#message-queue-patterns) 6. [Caching Strategy](#caching-strategy) 7. [Security Architecture](#security-architecture) 8. [Performance Characteristics](#performance-characteristics) 9. [Disaster Recovery](#disaster-recovery) --- ## High-Level Architecture CloudFlow follows a microservices architecture pattern deployed across multiple availability zones in AWS. The platform is designed with the following core principles: - **Scalability**: Horizontal scaling for all services with auto-scaling groups - **Resilience**: Circuit breakers, bulkheads, and graceful degradation - **Observability**: Distributed tracing, centralized logging, and comprehensive metrics - **Security**: Zero-trust network architecture with mTLS encryption ### Architecture Diagram (Conceptual) ``` \u250c\u2500\u2500\u2500\u2500\u2500\u2500\u2500\u2500\u2500\u2500\u2500\u2500\u2500\u2500\u2500\u2500\u2500\u2500\u2500\u2500\u2500\u2500\u2500\u2500\u2500\u2500\u2500\u2500\u2500\u2500\u2500\u2500\u2500\u2500\u2500\u2500\u2500\u2500\u2500\u2500\u2500\u2500\u2500\u2500\u2500\u2500\u2500\u2500\u2500\u2500\u2500\u2500\u2500\u2500\u2500\u2500\u2500\u2500\u2500\u2500\u2500\u2500\u2500\u2500\u2500\u2510 \u2502 Load Balancer (ALB) \u2502 \u2502 (TLS Termination - 443) \u2502 \u2514\u2500\u2500\u2500\u2500\u2500\u2500\u2500\u2500\u2500\u2500\u2500\u2500\u2500\u2500\u2500\u2500\u2500\u2500\u2500\u2500\u2500\u2500\u2500\u2500\u2500\u2500\u2500\u2500\u252c\u2500\u2500\u2500\u2500\u2500\u2500\u2500\u2500\u2500\u2500\u2500\u2500\u2500\u2500\u2500\u2500\u2500\u2500\u2500\u2500\u2500\u2500\u2500\u2500\u2500\u2500\u2500\u2500\u2500\u2500\u2500\u2500\u2500\u2500\u2500\u2500\u2518 \u2502 \u25bc \u250c\u2500\u2500\u2500\u2500\u2500\u2500\u2500\u2500\u2500\u2500\u2500\u2500\u2500\u2500\u2500\u2500\u2500\u2500\u2500\u2500\u2500\u2500\u2500\u2500\u2500\u2500\u2500\u2500\u2500\u2500\u2500\u2500\u2500\u2500\u2500\u2500\u2500\u2500\u2500\u2500\u2500\u2500\u2500\u2500\u2500\u2500\u2500\u2500\u2500\u2500\u2500\u2500\u2500\u2500\u2500\u2500\u2500\u2500\u2500\u2500\u2500\u2500\u2500\u2500\u2500\u2510 \u2502 API Gateway Layer \u2502 \u2502 (Rate Limiting, Auth, Request Routing) \u2502 \u2514\u2500\u252c\u2500\u2500\u2500\u2500\u2500\u2500\u2500\u252c\u2500\u2500\u2500\u2500\u2500\u2500\u2500\u2500\u2500\u2500\u252c\u2500\u2500\u2500\u2500\u2500\u2500\u2500\u2500\u2500\u2500\u2500\u2500\u252c\u2500\u2500\u2500\u2500\u2500\u2500\u2500\u2500\u2500\u2500\u2500\u2500\u2500\u2500\u252c\u2500\u2500\u2500\u2500\u2500\u2500\u2500\u2500\u2500\u2500\u2500\u2500\u2500\u2500\u2500\u2500\u2518 \u2502 \u2502 \u2502 \u2502 \u2502 \u25bc \u25bc \u25bc \u25bc \u25bc \u250c\u2500\u2500\u2500\u2500\u2510 \u250c\u2500\u2500\u2500\u2500\u2500\u2500\u2510 \u250c\u2500\u2500\u2500\u2500\u2500\u2500\u2500\u2500\u2500\u2500\u2510 \u250c\u2500\u2500\u2500\u2500\u2500\u2500\u2500\u2500\u2500\u2500\u2510 \u250c\u2500\u2500\u2500\u2500\u2500\u2500\u2500\u2500\u2500\u2500\u2500\u2500\u2500\u2500\u2510 \u2502Auth\u2502 \u2502Workflow\u2502 \u2502Scheduler\u2502 \u2502Notification\u2502 \u2502User Service\u2502 \u2502Svc \u2502 \u2502 Engine \u2502 \u2502 Service \u2502 \u2502 Service \u2502 \u2502 \u2502 \u2514\u2500\u252c\u2500\u2500\u2518 \u2514\u2500\u2500\u2500\u252c\u2500\u2500\u2500\u2500\u2518 \u2514\u2500\u2500\u2500\u2500\u252c\u2500\u2500\u2500\u2500\u2500\u2518 \u2514\u2500\u2500\u2500\u2500\u2500\u252c\u2500\u2500\u2500\u2500\u2518 \u2514\u2500\u2500\u2500\u2500\u2500\u2500\u252c\u2500\u2500\u2500\u2500\u2500\u2518 \u2502 \u2502 \u2502 \u2502 \u2502 \u2514\u2500\u2500\u2500\u2500\u2500\u2500\u2500\u2500\u2534\u2500\u2500\u2500\u2500\u2500\u2500\u2500\u2500\u2500\u2500\u2500\u2534\u2500\u2500\u2500\u2500\u2500\u2500\u2500\u2500\u2500\u2500\u2500\u2500\u2500\u2534\u2500\u2500\u2500\u2500\u2500\u2500\u2500\u2500\u2500\u2500\u2500\u2500\u2500\u2500\u2518 \u2502 \u250c\u2500\u2500\u2500\u2500\u2500\u2500\u2500\u2500\u2500\u2500\u2500\u2500\u2500\u2500\u2500\u253c\u2500\u2500\u2500\u2500\u2500\u2500\u2500\u2500\u2500\u2500\u2500\u2500\u2500\u2500\u2500\u2510 \u2502 \u2502 \u2502 \u25bc \u25bc \u25bc \u250c\u2500\u2500\u2500\u2500\u2500\u2500\u2500\u2500\u2500\u2510 \u250c\u2500\u2500\u2500\u2500\u2500\u2500\u2500\u2500\u2500\u2500\u2510 \u250c\u2500\u2500\u2500\u2500\u2500\u2500\u2500\u2500\u2500\u2510 \u2502PostgreSQL\u2502 \u2502 Redis \u2502 \u2502 Kafka \u2502 \u2502 Cluster \u2502 \u2502 Cluster \u2502 \u2502 Cluster \u2502 \u2514\u2500\u2500\u2500\u2500\u2500\u2500\u2500\u2500\u2500\u2518 \u2514\u2500\u2500\u2500\u2500\u2500\u2500\u2500\u2500\u2500\u2500\u2518 \u2514\u2500\u2500\u2500\u2500\u2500\u2500\u2500\u2500\u2500\u2518 ``` ### Technology Stack - **Runtime**: Node.js 20.x (API Gateway, Workflow Engine), Go 1.21 (Auth Service, Scheduler) - **Container Orchestration**: Kubernetes 1.28 (EKS) - **Service Mesh**: Istio 1.20 for service-to-service communication - **Databases**: PostgreSQL 15.4, Redis 7.2 - **Message Broker**: Apache Kafka 3.6 - **Monitoring**: Prometheus, Grafana, Jaeger for distributed tracing - **Secrets Management**: HashiCorp Vault 1.15 --- ## Microservices Breakdown ### API Gateway **Purpose**: Single entry point for all client requests, providing authentication, rate limiting, request routing, and protocol translation.", "enhanced_content": "Executive Summary, Architecture Team, Document Version, Architecture, System Architecture, Platform Architecture, cloud-native workflow | Platform - System Architecture Overview **Document Version:**, P99, Contents 1, mTLS, Load Balancer\n\n# CloudFlow Platform - System Architecture Overview **Document Version:** 2.3.1 **Last Updated:** January 15, 2026 **Owner:** Platform Architecture Team **Status:** Production ## Executive Summary CloudFlow is a distributed, cloud-native workflow automation platform designed to orchestrate complex business processes at scale. The platform processes over 2.5 million workflow executions daily with an average P99 latency of 180ms for API operations and 4.2 seconds for workflow execution. This document provides a comprehensive overview of the system architecture, including microservices design, data flow patterns, infrastructure decisions, and operational considerations. ## Table of Contents 1. [High-Level Architecture](#high-level-architecture) 2. [Microservices Breakdown](#microservices-breakdown) 3. [Data Flow Architecture](#data-flow-architecture) 4. [Database Architecture](#database-architecture) 5. [Message Queue Patterns](#message-queue-patterns) 6. [Caching Strategy](#caching-strategy) 7. [Security Architecture](#security-architecture) 8. [Performance Characteristics](#performance-characteristics) 9. [Disaster Recovery](#disaster-recovery) --- ## High-Level Architecture CloudFlow follows a microservices architecture pattern deployed across multiple availability zones in AWS. The platform is designed with the following core principles: - **Scalability**: Horizontal scaling for all services with auto-scaling groups - **Resilience**: Circuit breakers, bulkheads, and graceful degradation - **Observability**: Distributed tracing, centralized logging, and comprehensive metrics - **Security**: Zero-trust network architecture with mTLS encryption ### Architecture Diagram (Conceptual) ``` \u250c\u2500\u2500\u2500\u2500\u2500\u2500\u2500\u2500\u2500\u2500\u2500\u2500\u2500\u2500\u2500\u2500\u2500\u2500\u2500\u2500\u2500\u2500\u2500\u2500\u2500\u2500\u2500\u2500\u2500\u2500\u2500\u2500\u2500\u2500\u2500\u2500\u2500\u2500\u2500\u2500\u2500\u2500\u2500\u2500\u2500\u2500\u2500\u2500\u2500\u2500\u2500\u2500\u2500\u2500\u2500\u2500\u2500\u2500\u2500\u2500\u2500\u2500\u2500\u2500\u2500\u2510 \u2502 Load Balancer (ALB) \u2502 \u2502 (TLS Termination - 443) \u2502 \u2514\u2500\u2500\u2500\u2500\u2500\u2500\u2500\u2500\u2500\u2500\u2500\u2500\u2500\u2500\u2500\u2500\u2500\u2500\u2500\u2500\u2500\u2500\u2500\u2500\u2500\u2500\u2500\u2500\u252c\u2500\u2500\u2500\u2500\u2500\u2500\u2500\u2500\u2500\u2500\u2500\u2500\u2500\u2500\u2500\u2500\u2500\u2500\u2500\u2500\u2500\u2500\u2500\u2500\u2500\u2500\u2500\u2500\u2500\u2500\u2500\u2500\u2500\u2500\u2500\u2500\u2518 \u2502 \u25bc \u250c\u2500\u2500\u2500\u2500\u2500\u2500\u2500\u2500\u2500\u2500\u2500\u2500\u2500\u2500\u2500\u2500\u2500\u2500\u2500\u2500\u2500\u2500\u2500\u2500\u2500\u2500\u2500\u2500\u2500\u2500\u2500\u2500\u2500\u2500\u2500\u2500\u2500\u2500\u2500\u2500\u2500\u2500\u2500\u2500\u2500\u2500\u2500\u2500\u2500\u2500\u2500\u2500\u2500\u2500\u2500\u2500\u2500\u2500\u2500\u2500\u2500\u2500\u2500\u2500\u2500\u2510 \u2502 API Gateway Layer \u2502 \u2502 (Rate Limiting, Auth, Request Routing) \u2502 \u2514\u2500\u252c\u2500\u2500\u2500\u2500\u2500\u2500\u2500\u252c\u2500\u2500\u2500\u2500\u2500\u2500\u2500\u2500\u2500\u2500\u252c\u2500\u2500\u2500\u2500\u2500\u2500\u2500\u2500\u2500\u2500\u2500\u2500\u252c\u2500\u2500\u2500\u2500\u2500\u2500\u2500\u2500\u2500\u2500\u2500\u2500\u2500\u2500\u252c\u2500\u2500\u2500\u2500\u2500\u2500\u2500\u2500\u2500\u2500\u2500\u2500\u2500\u2500\u2500\u2500\u2518 \u2502 \u2502 \u2502 \u2502 \u2502 \u25bc \u25bc \u25bc \u25bc \u25bc \u250c\u2500\u2500\u2500\u2500\u2510 \u250c\u2500\u2500\u2500\u2500\u2500\u2500\u2510 \u250c\u2500\u2500\u2500\u2500\u2500\u2500\u2500\u2500\u2500\u2500\u2510 \u250c\u2500\u2500\u2500\u2500\u2500\u2500\u2500\u2500\u2500\u2500\u2510 \u250c\u2500\u2500\u2500\u2500\u2500\u2500\u2500\u2500\u2500\u2500\u2500\u2500\u2500\u2500\u2510 \u2502Auth\u2502 \u2502Workflow\u2502 \u2502Scheduler\u2502 \u2502Notification\u2502 \u2502User Service\u2502 \u2502Svc \u2502 \u2502 Engine \u2502 \u2502 Service \u2502 \u2502 Service \u2502 \u2502 \u2502 \u2514\u2500\u252c\u2500\u2500\u2518 \u2514\u2500\u2500\u2500\u252c\u2500\u2500\u2500\u2500\u2518 \u2514\u2500\u2500\u2500\u2500\u252c\u2500\u2500\u2500\u2500\u2500\u2518 \u2514\u2500\u2500\u2500\u2500\u2500\u252c\u2500\u2500\u2500\u2500\u2518 \u2514\u2500\u2500\u2500\u2500\u2500\u2500\u252c\u2500\u2500\u2500\u2500\u2500\u2518 \u2502 \u2502 \u2502 \u2502 \u2502 \u2514\u2500\u2500\u2500\u2500\u2500\u2500\u2500\u2500\u2534\u2500\u2500\u2500\u2500\u2500\u2500\u2500\u2500\u2500\u2500\u2500\u2534\u2500\u2500\u2500\u2500\u2500\u2500\u2500\u2500\u2500\u2500\u2500\u2500\u2500\u2534\u2500\u2500\u2500\u2500\u2500\u2500\u2500\u2500\u2500\u2500\u2500\u2500\u2500\u2500\u2518 \u2502 \u250c\u2500\u2500\u2500\u2500\u2500\u2500\u2500\u2500\u2500\u2500\u2500\u2500\u2500\u2500\u2500\u253c\u2500\u2500\u2500\u2500\u2500\u2500\u2500\u2500\u2500\u2500\u2500\u2500\u2500\u2500\u2500\u2510 \u2502 \u2502 \u2502 \u25bc \u25bc \u25bc \u250c\u2500\u2500\u2500\u2500\u2500\u2500\u2500\u2500\u2500\u2510 \u250c\u2500\u2500\u2500\u2500\u2500\u2500\u2500\u2500\u2500\u2500\u2510 \u250c\u2500\u2500\u2500\u2500\u2500\u2500\u2500\u2500\u2500\u2510 \u2502PostgreSQL\u2502 \u2502 Redis \u2502 \u2502 Kafka \u2502 \u2502 Cluster \u2502 \u2502 Cluster \u2502 \u2502 Cluster \u2502 \u2514\u2500\u2500\u2500\u2500\u2500\u2500\u2500\u2500\u2500\u2518 \u2514\u2500\u2500\u2500\u2500\u2500\u2500\u2500\u2500\u2500\u2500\u2518 \u2514\u2500\u2500\u2500\u2500\u2500\u2500\u2500\u2500\u2500\u2518 ``` ### Technology Stack - **Runtime**: Node.js 20.x (API Gateway, Workflow Engine), Go 1.21 (Auth Service, Scheduler) - **Container Orchestration**: Kubernetes 1.28 (EKS) - **Service Mesh**: Istio 1.20 for service-to-service communication - **Databases**: PostgreSQL 15.4, Redis 7.2 - **Message Broker**: Apache Kafka 3.6 - **Monitoring**: Prometheus, Grafana, Jaeger for distributed tracing - **Secrets Management**: HashiCorp Vault 1.15 --- ## Microservices Breakdown ### API Gateway **Purpose**: Single entry point for all client requests, providing authentication, rate limiting, request routing, and protocol translation.", "enrichment_type": "fast", "metadata": {"code_ratio": 0.28, "processing_time_ms": 143.37, "keyword_count": 10, "entity_count": 14}, "keywords": ["Executive Summary", "Architecture Team", "Document Version", "Architecture", "System Architecture", "Platform Architecture", "cloud-native workflow", "workflow automation", "automation platform", "API Gateway"], "questions": [], "summary": "", "entities": {"ORG": ["Platform - System Architecture Overview **Document Version:**", "P99", "API", "Data Flow Architecture](#data-flow", "AWS"], "LAW": ["Contents 1"], "GPE": ["mTLS"], "PERSON": ["Load Balancer", "API Gateway Layer", "\u2502", "\u2514\u2500\u252c\u2500\u2500\u2500\u2500\u2500\u2500\u2500", "Workflow"], "PRODUCT": ["Termination - 443", "\u2518 ```"]}, "contextual_prefix": ""}