{"original_content": "**Technology**: Go with distributed locking via Redis **Replicas**: 4 pods (production), active-passive with leader election **Resource Allocation**: 2 vCPU, 4GB RAM per pod **Key Responsibilities**: - Parse and validate cron expressions (extended format supporting seconds) - Maintain schedule registry in PostgreSQL - Distributed scheduling with leader election (one active scheduler) - Missed execution handling with configurable catch-up policy - Schedule conflict detection and resolution - Time zone support for international schedules **Scheduling Architecture**: ``` PostgreSQL Schedules Table \u2502 \u25bc Leader Scheduler (elected via Redis) \u2502 \u251c\u2500 Scan for due schedules (every 10 seconds) \u251c\u2500 Acquire lock per schedule (prevents duplicates) \u251c\u2500 Publish to Kafka \u2192 workflow.events topic \u2514\u2500 Update last_run timestamp ``` **Schedule Types**: - **Cron-based**: `0 */5 * * * *` (every 5 minutes) - **One-time**: Specific timestamp for delayed execution - **Interval-based**: Every N seconds/minutes/hours **Reliability Features**: - Leader election using Redis with 30-second lease - Heartbeat mechanism to detect leader failure (5-second interval) - Automatic failover to standby scheduler (< 10 seconds) - Schedule versioning to handle updates during execution - Missed execution policy: SKIP, RUN_ONCE, or RUN_ALL **Performance Targets**: - Schedule evaluation: < 100ms per cycle - Accuracy: \u00b1 1 second for schedule triggers - Capacity: 100,000 active schedules --- ### Notification Service **Purpose**: Multi-channel notification delivery system supporting email, SMS, webhooks, and in-app notifications.", "enhanced_content": "leader election, Missed execution, Resource Allocation, Key Responsibilities, Reliability Features, Performance Targets, Scheduling Architecture | PostgreSQL, Leader Scheduler, Kafka, Redis, SMS\n\n**Technology**: Go with distributed locking via Redis **Replicas**: 4 pods (production), active-passive with leader election **Resource Allocation**: 2 vCPU, 4GB RAM per pod **Key Responsibilities**: - Parse and validate cron expressions (extended format supporting seconds) - Maintain schedule registry in PostgreSQL - Distributed scheduling with leader election (one active scheduler) - Missed execution handling with configurable catch-up policy - Schedule conflict detection and resolution - Time zone support for international schedules **Scheduling Architecture**: ``` PostgreSQL Schedules Table \u2502 \u25bc Leader Scheduler (elected via Redis) \u2502 \u251c\u2500 Scan for due schedules (every 10 seconds) \u251c\u2500 Acquire lock per schedule (prevents duplicates) \u251c\u2500 Publish to Kafka \u2192 workflow.events topic \u2514\u2500 Update last_run timestamp ``` **Schedule Types**: - **Cron-based**: `0 */5 * * * *` (every 5 minutes) - **One-time**: Specific timestamp for delayed execution - **Interval-based**: Every N seconds/minutes/hours **Reliability Features**: - Leader election using Redis with 30-second lease - Heartbeat mechanism to detect leader failure (5-second interval) - Automatic failover to standby scheduler (< 10 seconds) - Schedule versioning to handle updates during execution - Missed execution policy: SKIP, RUN_ONCE, or RUN_ALL **Performance Targets**: - Schedule evaluation: < 100ms per cycle - Accuracy: \u00b1 1 second for schedule triggers - Capacity: 100,000 active schedules --- ### Notification Service **Purpose**: Multi-channel notification delivery system supporting email, SMS, webhooks, and in-app notifications.", "enrichment_type": "fast", "metadata": {"code_ratio": 0.16, "processing_time_ms": 59.04, "keyword_count": 10, "entity_count": 6}, "keywords": ["leader election", "Missed execution", "Resource Allocation", "Key Responsibilities", "Reliability Features", "Performance Targets", "Scheduling Architecture", "Leader Scheduler", "Notification Service", "Multi-channel notification"], "questions": [], "summary": "", "entities": {"GPE": ["PostgreSQL"], "PERSON": ["Leader Scheduler", "Kafka"], "ORG": ["Redis", "SMS"], "NORP": ["Scan"]}, "contextual_prefix": ""}