{"original_content": "Open the Visual Editor by clicking **\"Create Workflow\"** or editing an existing workflow 2. Add a trigger by clicking the **\"Add Trigger\"** button 3. Configure your trigger settings in the right panel 4. Add actions by clicking the **\"+\"** button below any step 5. Connect conditional branches by adding **\"Condition\"** blocks 6. Use the **\"Test\"** button to validate your workflow with sample data ### YAML Definition For advanced users and version control integration, CloudFlow supports YAML-based workflow definitions: ```yaml name: \"Process Customer Orders\" description: \"Validates and processes new customer orders\" version: \"1.0\" trigger: type: webhook method: POST path: /orders/new steps: - id: validate_order name: \"Validate Order Data\" action: javascript code: | if (!input.order_id || !input.customer_email) { throw new Error(\"Missing required fields\"); } return { valid: true }; - id: check_inventory name: \"Check Inventory\" action: http_request config: method: GET url: \"https://api.inventory.example.com/check\" params: product_id: \"{{trigger.body.product_id}}\" headers: Authorization: \"Bearer {{secrets.INVENTORY_API_KEY}}\" - id: send_confirmation name: \"Send Confirmation Email\" action: email config: to: \"{{trigger.body.customer_email}}\" subject: \"Order Confirmation - #{{trigger.body.order_id}}\" body: \"Thank you for your order! Your order #{{trigger.body.order_id}} has been confirmed.\" ``` **Benefits of YAML Definitions:** - Version control friendly (commit to Git) - Easy to share and duplicate workflows - Supports comments and documentation - Can be generated programmatically - Enables infrastructure-as-code practices To import a YAML workflow, click **\"Import\"** > **\"From YAML\"** in your dashboard. ### Triggers Triggers determine when your workflow runs. CloudFlow supports several trigger types: **Webhook Triggers** Receive HTTP requests at a unique URL to start your workflow: - Support GET, POST, PUT, PATCH, DELETE methods - Automatically parse JSON and form data - Access headers, query parameters, and body in your workflow **Schedule Triggers** Run workflows on a recurring schedule (see [Scheduling](#scheduling) for details) **Event Triggers** Respond to events from integrated applications: - New email received (Gmail, Outlook) - File uploaded (Google Drive, Dropbox, S3) - Database record created or updated - Form submission (Typeform, Google Forms) - Chat message (Slack, Discord) **Manual Triggers** Start workflows on-demand from the dashboard or via API ## Available Actions CloudFlow provides a comprehensive library of actions to build powerful automations.", "enhanced_content": "Visual Editor, Create Workflow, Triggers, Workflow, Create, Visual, Editor | CloudFlow, YAML, Git, JSON, Google Drive\n\nOpen the Visual Editor by clicking **\"Create Workflow\"** or editing an existing workflow 2. Add a trigger by clicking the **\"Add Trigger\"** button 3. Configure your trigger settings in the right panel 4. Add actions by clicking the **\"+\"** button below any step 5. Connect conditional branches by adding **\"Condition\"** blocks 6. Use the **\"Test\"** button to validate your workflow with sample data ### YAML Definition For advanced users and version control integration, CloudFlow supports YAML-based workflow definitions: ```yaml name: \"Process Customer Orders\" description: \"Validates and processes new customer orders\" version: \"1.0\" trigger: type: webhook method: POST path: /orders/new steps: - id: validate_order name: \"Validate Order Data\" action: javascript code: | if (!input.order_id || !input.customer_email) { throw new Error(\"Missing required fields\"); } return { valid: true }; - id: check_inventory name: \"Check Inventory\" action: http_request config: method: GET url: \"https://api.inventory.example.com/check\" params: product_id: \"{{trigger.body.product_id}}\" headers: Authorization: \"Bearer {{secrets.INVENTORY_API_KEY}}\" - id: send_confirmation name: \"Send Confirmation Email\" action: email config: to: \"{{trigger.body.customer_email}}\" subject: \"Order Confirmation - #{{trigger.body.order_id}}\" body: \"Thank you for your order! Your order #{{trigger.body.order_id}} has been confirmed.\" ``` **Benefits of YAML Definitions:** - Version control friendly (commit to Git) - Easy to share and duplicate workflows - Supports comments and documentation - Can be generated programmatically - Enables infrastructure-as-code practices To import a YAML workflow, click **\"Import\"** > **\"From YAML\"** in your dashboard. ### Triggers Triggers determine when your workflow runs. CloudFlow supports several trigger types: **Webhook Triggers** Receive HTTP requests at a unique URL to start your workflow: - Support GET, POST, PUT, PATCH, DELETE methods - Automatically parse JSON and form data - Access headers, query parameters, and body in your workflow **Schedule Triggers** Run workflows on a recurring schedule (see [Scheduling](#scheduling) for details) **Event Triggers** Respond to events from integrated applications: - New email received (Gmail, Outlook) - File uploaded (Google Drive, Dropbox, S3) - Database record created or updated - Form submission (Typeform, Google Forms) - Chat message (Slack, Discord) **Manual Triggers** Start workflows on-demand from the dashboard or via API ## Available Actions CloudFlow provides a comprehensive library of actions to build powerful automations.", "enrichment_type": "fast", "metadata": {"code_ratio": 0.34, "processing_time_ms": 52.83, "keyword_count": 10, "entity_count": 10}, "keywords": ["Visual Editor", "Create Workflow", "Triggers", "Workflow", "Create", "Visual", "Editor", "YAML", "clicking", "trigger"], "questions": [], "summary": "", "entities": {"ORG": ["CloudFlow", "YAML", "POST", "PUT", "Gmail, Outlook) -"], "PERSON": ["Git", "JSON", "[Scheduling](#scheduling"], "FAC": ["Google Drive"], "GPE": ["Dropbox"]}, "contextual_prefix": ""}