{"original_content": "# CloudFlow API Reference Version 2.1.0 | Last Updated: January 2026 ## Overview The CloudFlow API is a RESTful service that enables developers to programmatically manage cloud workflows, data pipelines, and automation tasks. This documentation provides comprehensive details on authentication, endpoints, request/response formats, error handling, and best practices. **Base URL:** `https://api.cloudflow.io/v2` **API Status:** https://status.cloudflow.io ## Authentication CloudFlow supports three authentication methods to suit different use cases and security requirements. ### API Keys API keys provide simple authentication for server-to-server communication. Include your API key in the request header: ```bash curl -H \"X-API-Key: cf_live_a1b2c3d4e5f6g7h8i9j0\" \\ https://api.cloudflow.io/v2/workflows ``` **Security Notes:** - Never expose API keys in client-side code - Rotate keys every 90 days - Use separate keys for development and production environments ### OAuth 2.0 OAuth 2.0 is recommended for applications that access CloudFlow on behalf of users. We support the Authorization Code flow with PKCE. **Authorization Endpoint:** `https://auth.cloudflow.io/oauth/authorize` **Token Endpoint:** `https://auth.cloudflow.io/oauth/token` **Supported Scopes:** - `workflows:read` - Read workflow configurations - `workflows:write` - Create and modify workflows - `pipelines:read` - Read pipeline data - `pipelines:write` - Create and manage pipelines - `analytics:read` - Access analytics and metrics - `admin:full` - Full administrative access Example authorization request: ```bash curl -X POST https://auth.cloudflow.io/oauth/token \\ -H \"Content-Type: application/x-www-form-urlencoded\" \\ -d \"grant_type=authorization_code\" \\ -d \"code=AUTH_CODE_HERE\" \\ -d \"client_id=YOUR_CLIENT_ID\" \\ -d \"client_secret=YOUR_CLIENT_SECRET\" \\ -d \"redirect_uri=https://yourapp.com/callback\" ``` ### JWT Tokens For advanced use cases, CloudFlow supports JSON Web Tokens (JWT) with RS256 signing algorithm. JWTs must include the following claims: - `iss` (issuer): Your application identifier - `sub` (subject): User or service account ID - `aud` (audience): `https://api.cloudflow.io` - `exp` (expiration): Unix timestamp (max 3600 seconds from `iat`) - `iat` (issued at): Unix timestamp - `scope`: Space-separated list of requested scopes Example JWT header: ```python import jwt import time from cryptography.hazmat.primitives import serialization from cryptography.hazmat.backends import default_backend # Load your private key with open('private_key.pem', 'rb') as key_file: private_key = serialization.load_pem_private_key( key_file.read(), password=None, backend=default_backend() ) # Create JWT payload payload = { 'iss': 'your-app-id', 'sub': 'user-12345', 'aud': 'https://api.cloudflow.io', 'exp': int(time.time()) + 3600, 'iat': int(time.time()), 'scope': 'workflows:read workflows:write' } # Generate token token = jwt.encode(payload, private_key, algorithm='RS256') # Use in API request headers = {'Authorization': f'Bearer {token}'} ``` **Token Expiration:** All tokens expire after 3600 seconds (1 hour). Implement token refresh logic in your application.", "enhanced_content": "Reference Version, API Reference, API, API Keys, automation tasks, January, enables developers | API, CloudFlow, API Keys API, JWT Tokens, the Authorization Code\n\n# CloudFlow API Reference Version 2.1.0 | Last Updated: January 2026 ## Overview The CloudFlow API is a RESTful service that enables developers to programmatically manage cloud workflows, data pipelines, and automation tasks. This documentation provides comprehensive details on authentication, endpoints, request/response formats, error handling, and best practices. **Base URL:** `https://api.cloudflow.io/v2` **API Status:** https://status.cloudflow.io ## Authentication CloudFlow supports three authentication methods to suit different use cases and security requirements. ### API Keys API keys provide simple authentication for server-to-server communication. Include your API key in the request header: ```bash curl -H \"X-API-Key: cf_live_a1b2c3d4e5f6g7h8i9j0\" \\ https://api.cloudflow.io/v2/workflows ``` **Security Notes:** - Never expose API keys in client-side code - Rotate keys every 90 days - Use separate keys for development and production environments ### OAuth 2.0 OAuth 2.0 is recommended for applications that access CloudFlow on behalf of users. We support the Authorization Code flow with PKCE. **Authorization Endpoint:** `https://auth.cloudflow.io/oauth/authorize` **Token Endpoint:** `https://auth.cloudflow.io/oauth/token` **Supported Scopes:** - `workflows:read` - Read workflow configurations - `workflows:write` - Create and modify workflows - `pipelines:read` - Read pipeline data - `pipelines:write` - Create and manage pipelines - `analytics:read` - Access analytics and metrics - `admin:full` - Full administrative access Example authorization request: ```bash curl -X POST https://auth.cloudflow.io/oauth/token \\ -H \"Content-Type: application/x-www-form-urlencoded\" \\ -d \"grant_type=authorization_code\" \\ -d \"code=AUTH_CODE_HERE\" \\ -d \"client_id=YOUR_CLIENT_ID\" \\ -d \"client_secret=YOUR_CLIENT_SECRET\" \\ -d \"redirect_uri=https://yourapp.com/callback\" ``` ### JWT Tokens For advanced use cases, CloudFlow supports JSON Web Tokens (JWT) with RS256 signing algorithm. JWTs must include the following claims: - `iss` (issuer): Your application identifier - `sub` (subject): User or service account ID - `aud` (audience): `https://api.cloudflow.io` - `exp` (expiration): Unix timestamp (max 3600 seconds from `iat`) - `iat` (issued at): Unix timestamp - `scope`: Space-separated list of requested scopes Example JWT header: ```python import jwt import time from cryptography.hazmat.primitives import serialization from cryptography.hazmat.backends import default_backend # Load your private key with open('private_key.pem', 'rb') as key_file: private_key = serialization.load_pem_private_key( key_file.read(), password=None, backend=default_backend() ) # Create JWT payload payload = { 'iss': 'your-app-id', 'sub': 'user-12345', 'aud': 'https://api.cloudflow.io', 'exp': int(time.time()) + 3600, 'iat': int(time.time()), 'scope': 'workflows:read workflows:write' } # Generate token token = jwt.encode(payload, private_key, algorithm='RS256') # Use in API request headers = {'Authorization': f'Bearer {token}'} ``` **Token Expiration:** All tokens expire after 3600 seconds (1 hour). Implement token refresh logic in your application.", "enrichment_type": "fast", "metadata": {"code_ratio": 0.43, "processing_time_ms": 599.33, "keyword_count": 10, "entity_count": 11}, "keywords": ["Reference Version", "API Reference", "API", "API Keys", "automation tasks", "January", "enables developers", "Version", "Updated", "Overview"], "questions": [], "summary": "", "entities": {"ORG": ["API", "CloudFlow", "PKCE", "JWT"], "PERSON": ["API Keys API", "JWT Tokens", "JSON", "JWTs", "Example JWT"], "LAW": ["the Authorization Code"], "PRODUCT": ["RS256"]}, "contextual_prefix": ""}