{"original_content": "Resume normal operations - Recovery time: 1-3 hours depending on data volume - Data loss: None if corruption detected quickly ### Testing & Validation **DR Drill Schedule**: - Monthly: Automated failover test (single AZ failure simulation) - Quarterly: Full DR region failover (non-production hours) - Annually: Complete disaster simulation with all stakeholders **Last DR Test Results** (Dec 15, 2025): - Scenario: Full region failover - Actual RTO: 2 hours 23 minutes (target: 4 hours) - Actual RPO: 42 minutes (target: 1 hour) - Issues identified: DNS propagation slower than expected (resolved) - Success criteria: Met all recovery objectives ### Business Continuity **Communication Plan**: - Status page: status.cloudflow.com (updated every 15 minutes during incident) - Customer notifications: Email + SMS for all P1 incidents - Internal escalation: PagerDuty \u2192 Incident Commander \u2192 Engineering Manager \u2192 CTO **Data Retention Policy**: - Active data: 12 months in hot storage (PostgreSQL) - Archived data: 7 years in cold storage (S3 Glacier) - Audit logs: 7 years (compliance requirement) - Backup retention: 30 days standard, 90 days monthly snapshots --- ## Appendix ### Service Dependency Matrix | Service | Depends On | Critical Path | |---------|-----------|---------------| | API Gateway | Auth Service, Redis | Yes | | Auth Service | PostgreSQL, Redis, Vault | Yes | | Workflow Engine | PostgreSQL, Kafka, Redis | Yes | | Scheduler | PostgreSQL, Redis, Kafka | No | | Notification Service | Kafka, PostgreSQL, SendGrid, Twilio | No | ### Capacity Planning **Current Capacity** (Jan 2026): - Daily workflow executions: 2.5M - Active users: 150,000 - API requests per day: 50M - Database size: 1.2TB - Kafka throughput: 100K msg/sec peak **6-Month Projection** (Jul 2026): - Daily workflow executions: 4M (+60%) - Active users: 225,000 (+50%) - API requests per day: 80M (+60%) - Database size: 2TB (+67%) - Required scaling: +30% compute, +50% storage ### Contact Information - **Architecture Team**: architecture@cloudflow.internal - **On-Call Engineer**: PagerDuty escalation - **Security Team**: security@cloudflow.internal - **Documentation**: https://wiki.cloudflow.internal/architecture --- **Document Revision History**: - v2.3.1 (Jan 15, 2026): Updated performance metrics, added DR test results - v2.3.0 (Dec 1, 2025): Added multi-AZ deployment details - v2.2.0 (Oct 15, 2025): Security architecture overhaul - v2.1.0 (Sep 1, 2025): Initial Kafka migration documentation - v2.0.0 (Jul 1, 2025): Complete microservices rewrite", "enhanced_content": "Database size, Active users, Auth Service, Daily workflow, API requests, API Gateway, Test Results | AZ, DNS, P1, Critical Path, API Gateway\n\nResume normal operations - Recovery time: 1-3 hours depending on data volume - Data loss: None if corruption detected quickly ### Testing & Validation **DR Drill Schedule**: - Monthly: Automated failover test (single AZ failure simulation) - Quarterly: Full DR region failover (non-production hours) - Annually: Complete disaster simulation with all stakeholders **Last DR Test Results** (Dec 15, 2025): - Scenario: Full region failover - Actual RTO: 2 hours 23 minutes (target: 4 hours) - Actual RPO: 42 minutes (target: 1 hour) - Issues identified: DNS propagation slower than expected (resolved) - Success criteria: Met all recovery objectives ### Business Continuity **Communication Plan**: - Status page: status.cloudflow.com (updated every 15 minutes during incident) - Customer notifications: Email + SMS for all P1 incidents - Internal escalation: PagerDuty \u2192 Incident Commander \u2192 Engineering Manager \u2192 CTO **Data Retention Policy**: - Active data: 12 months in hot storage (PostgreSQL) - Archived data: 7 years in cold storage (S3 Glacier) - Audit logs: 7 years (compliance requirement) - Backup retention: 30 days standard, 90 days monthly snapshots --- ## Appendix ### Service Dependency Matrix | Service | Depends On | Critical Path | |---------|-----------|---------------| | API Gateway | Auth Service, Redis | Yes | | Auth Service | PostgreSQL, Redis, Vault | Yes | | Workflow Engine | PostgreSQL, Kafka, Redis | Yes | | Scheduler | PostgreSQL, Redis, Kafka | No | | Notification Service | Kafka, PostgreSQL, SendGrid, Twilio | No | ### Capacity Planning **Current Capacity** (Jan 2026): - Daily workflow executions: 2.5M - Active users: 150,000 - API requests per day: 50M - Database size: 1.2TB - Kafka throughput: 100K msg/sec peak **6-Month Projection** (Jul 2026): - Daily workflow executions: 4M (+60%) - Active users: 225,000 (+50%) - API requests per day: 80M (+60%) - Database size: 2TB (+67%) - Required scaling: +30% compute, +50% storage ### Contact Information - **Architecture Team**: architecture@cloudflow.internal - **On-Call Engineer**: PagerDuty escalation - **Security Team**: security@cloudflow.internal - **Documentation**: https://wiki.cloudflow.internal/architecture --- **Document Revision History**: - v2.3.1 (Jan 15, 2026): Updated performance metrics, added DR test results - v2.3.0 (Dec 1, 2025): Added multi-AZ deployment details - v2.2.0 (Oct 15, 2025): Security architecture overhaul - v2.1.0 (Sep 1, 2025): Initial Kafka migration documentation - v2.0.0 (Jul 1, 2025): Complete microservices rewrite", "enrichment_type": "fast", "metadata": {"code_ratio": 0.0, "processing_time_ms": 78.44, "keyword_count": 10, "entity_count": 16}, "keywords": ["Database size", "Active users", "Auth Service", "Daily workflow", "API requests", "API Gateway", "Test Results", "Business Continuity", "Communication Plan", "Engineering Manager"], "questions": [], "summary": "", "entities": {"ORG": ["AZ", "DNS", "Auth Service", "Vault", "Twilio"], "PRODUCT": ["P1"], "PERSON": ["Critical Path", "API Gateway", "Redis", "Kafka", "Scheduler"], "GPE": ["PostgreSQL", "Redis", "Kafka", "SendGrid"], "LAW": ["Sep 1, 2025"]}, "contextual_prefix": ""}